COPYING
MANIFEST.in
README.rst
bootstrap-buildout.py
buildout-develop.cfg
buildout-without-csu.cfg
buildout.cfg
requirements.txt
setup.py
version.txt
bob/__init__.py
bob.chapter.FRICE.egg-info/PKG-INFO
bob.chapter.FRICE.egg-info/SOURCES.txt
bob.chapter.FRICE.egg-info/dependency_links.txt
bob.chapter.FRICE.egg-info/entry_points.txt
bob.chapter.FRICE.egg-info/requires.txt
bob.chapter.FRICE.egg-info/top_level.txt
bob/chapter/__init__.py
bob/chapter/FRICE/__init__.py
bob/chapter/FRICE/tests.py
bob/chapter/FRICE/configurations/Graphs.py
bob/chapter/FRICE/configurations/ISV.py
bob/chapter/FRICE/configurations/LGBPHS.py
bob/chapter/FRICE/configurations/__init__.py
bob/chapter/FRICE/configurations/grid.py
bob/chapter/FRICE/configurations/image_preprocessor.py
bob/chapter/FRICE/configurations/image_resolution.py
bob/chapter/FRICE/configurations/optimized.py
bob/chapter/FRICE/databases/__init__.py
bob/chapter/FRICE/databases/arface.py
bob/chapter/FRICE/databases/mobio.py
bob/chapter/FRICE/databases/xm2vts.py
bob/chapter/FRICE/databases/youtube.py
bob/chapter/FRICE/script/__init__.py
bob/chapter/FRICE/script/configuration_optimization.py
bob/chapter/FRICE/script/expression.py
bob/chapter/FRICE/script/image_databases.py
bob/chapter/FRICE/script/image_preprocessor.py
bob/chapter/FRICE/script/image_resolution.py
bob/chapter/FRICE/script/occlusion.py
bob/chapter/FRICE/script/pose.py
bob/chapter/FRICE/script/timing.py
bob/chapter/FRICE/script/tools.py
bob/chapter/FRICE/script/video_databases.py
doc/algorithms.rst
doc/conf.py
doc/experiments.rst
doc/index.rst
doc/installation.rst
doc/links.rst