Metadata-Version: 1.1
Name: bob.chapter.FRICE
Version: 1.0.2
Summary: Running the experiments as described in the boock chapter "Face Recognition in Challenging Environments: An Experimental and Reproducible Research Survey"
Home-page: UNKNOWN
Author: Manuel Guenther
Author-email: siebenkopf@googlemail.com
License: GPLv3
Keywords: bob,face recognition
Platform: UNKNOWN
Classifier: Framework :: Bob
Classifier: Development Status :: 4 - Beta
Classifier: Intended Audience :: Developers
Classifier: License :: OSI Approved :: GNU General Public License v3 (GPLv3)
Classifier: Natural Language :: English
Classifier: Programming Language :: Python
Classifier: Topic :: Scientific/Engineering :: Artificial Intelligence
